macumba/__init__.py
macumba/api.py
macumba/cli.py
macumba/errors.py
macumba/jobs.py
macumba/v1.py
macumba/v2.py
macumba/ws.py
macumba-0.9.3.dist-info/DESCRIPTION.rst
macumba-0.9.3.dist-info/METADATA
macumba-0.9.3.dist-info/RECORD
macumba-0.9.3.dist-info/WHEEL
macumba-0.9.3.dist-info/entry_points.txt
macumba-0.9.3.dist-info/metadata.json
macumba-0.9.3.dist-info/top_level.txt
