Metadata-Version: 2.0
Name: macumba
Version: 0.9.3
Summary: Python 3 bindings for Juju
Home-page: https://github.com/Ubuntu-Solutions-Engineering/macumba
Author: Canonical Solutions Engineering
Author-email: ubuntu-dev@lists.ubuntu.com
License: LGPL-3
Platform: UNKNOWN
Requires-Dist: PyYAML
Requires-Dist: requests
Requires-Dist: ws4py
